{
  "date": "2025-09-29",
  "archived_at": "2026-04-26T03:27:47.314620+00:00",
  "source": "steam",
  "item_count": 3,
  "items": [
    {
      "title": "[正面] Tulu the goat",
      "summary": "Tulu the goat",
      "source": "steam_review",
      "platform_region": "global",
      "lang": "english",
      "time": "2025-09-29T12:01:47+00:00",
      "url": "https://steamcommunity.com/profiles/76561198059316348/recommended/3052450",
      "engagement": 0,
      "is_hot": false,
      "author": "76561198059316348",
      "tags": [],
      "content_type": "text",
      "media_url": ""
    },
    {
      "title": "[正面] muy buen gameplay, se disfruta bastante",
      "summary": "muy buen gameplay, se disfruta bastante",
      "source": "steam_review",
      "platform_region": "global",
      "lang": "spanish",
      "time": "2025-09-28T23:56:00+00:00",
      "url": "https://steamcommunity.com/profiles/76561199770565369/recommended/3052450",
      "engagement": 0,
      "is_hot": false,
      "author": "76561199770565369",
      "tags": [],
      "content_type": "text",
      "media_url": ""
    },
    {
      "title": "[正面] tulu is very pretty",
      "summary": "tulu is very pretty",
      "source": "steam_review",
      "platform_region": "global",
      "lang": "english",
      "time": "2025-09-28T19:05:46+00:00",
      "url": "https://steamcommunity.com/profiles/76561199811152689/recommended/3052450",
      "engagement": 0,
      "is_hot": false,
      "author": "76561199811152689",
      "tags": [],
      "content_type": "text",
      "media_url": ""
    }
  ]
}