{
  "date": "2026-02-02",
  "archived_at": "2026-04-26T03:27:29.452166+00:00",
  "source": "steam",
  "item_count": 1,
  "items": [
    {
      "title": "[正面] Was looking for something like this after Nier Rei...",
      "summary": "Was looking for something like this after Nier Reincarnation shut down. This is extremely generous for a gacha and super fun! Def pick this up if you like Slay the Spire.",
      "source": "steam_review",
      "platform_region": "global",
      "lang": "english",
      "time": "2026-02-02T03:05:07+00:00",
      "url": "https://steamcommunity.com/profiles/76561198079322907/recommended/3052450",
      "engagement": 1,
      "is_hot": false,
      "author": "76561198079322907",
      "tags": [],
      "content_type": "text",
      "media_url": ""
    }
  ]
}