{
  "_meta": {
    "source": "Voice.lua",
    "generated": "2026-06-16",
    "semantics": "每条为「关于某角色的闲话」,about=被议论角色(非说话者)。Voice.lua 无说话者字段,故不能据此做语音→说话者归属。",
    "use": "角色关系/八卦索引:谁被议论、议论内容(揭示角色间关系)",
    "total": 128,
    "distinct_about": 45
  },
  "by_subject": {
    "墨菲": [
      {
        "id": 5100,
        "about": "墨菲",
        "title": "闲话·关于墨菲",
        "content": "虽然性情不同，但我很喜欢那孩子。她身上有一种足以超脱一切困境与束缚的勇气。要是我也能那般勇敢和顽强，或许就不会选择投入大海的结局了吧……"
      },
      {
        "id": 5121,
        "about": "墨菲",
        "title": "闲话·关于墨菲",
        "content": "呵，我们的傀儡公主，又在哭哭啼啼了。是奶瓶不合嘴，还是摇篮曲不好听？"
      },
      {
        "id": 5546,
        "about": "墨菲",
        "title": "闲话·关于墨菲",
        "content": "伪造之物，脆弱如烟尘，丝缕清风就能吹散……"
      },
      {
        "id": 6034,
        "about": "墨菲",
        "title": "闲话·关于墨菲",
        "content": "和酒会上那些贵族小姐比起来，墨菲的脾气简直算得上可爱。"
      },
      {
        "id": 6201,
        "about": "墨菲",
        "title": "闲话·关于墨菲",
        "content": "那个人……对其他人那样的态度真的没问题吗？莎拉女士说，小孩子不可以随便发脾气……"
      },
      {
        "id": 6505,
        "about": "墨菲",
        "title": "闲话·关于「墨菲」",
        "content": "我当然知道，那是我的另一个侧面。但她为何要反抗？接受成为被选中者的命运，祈求之物不是信手拈来？"
      },
      {
        "id": 6696,
        "about": "墨菲",
        "title": "闲话·关于墨菲",
        "content": "那个叫墨菲的女人，穿得也太招摇了吧……不行，珈伦可不能输给她！"
      },
      {
        "id": 95068,
        "about": "墨菲",
        "title": "闲话：关于墨菲",
        "content": "听说她曾经也是一位圣女，不过，这样粗鲁的仪态、蛮横的言行……什么？她连一句祈祷的经文都不会背诵？如此毫无虔诚的样子，真让人有些为她的神明汗颜。"
      },
      {
        "id": 123803,
        "about": "墨菲",
        "title": "闲话：关于墨菲",
        "content": "我承认她很可爱……嗯，没错，看她和那些流浪在校园里的野猫追逐、打架确实挺可爱的。"
      }
    ],
    "詹金": [
      {
        "id": 5760,
        "about": "詹金",
        "title": "闲话·关于詹金",
        "content": "希望詹金和布朗在学院里过得开心，父亲的袖扣同她的自在比起来，不值一提，我相信他还有一整盒备用的。"
      },
      {
        "id": 5831,
        "about": "詹金",
        "title": "闲话·关于詹金",
        "content": "不好意思，你有见到我的螺丝吗？真奇怪啊，只要有那个老鼠耳朵的孩子在，我好像更容易忘了自己都把东西放到哪儿去了……"
      },
      {
        "id": 5889,
        "about": "詹金",
        "title": "闲话·关于詹金",
        "content": "啊，布朗跑过去了！我、我还是回避一下好了……"
      },
      {
        "id": 5919,
        "about": "詹金",
        "title": "闲话·关于詹金",
        "content": "那个小鬼很有灵性，街头生存就需要这种智慧。如果我还在外面探案的话，肯定会和她搞好关系的。"
      },
      {
        "id": 6274,
        "about": "詹金",
        "title": "闲话·关于詹金",
        "content": "听说来了个贫民窟的小偷，还带着一只胖老鼠？呵呵呵呵......看我替天行道，为主人铲除祸患！"
      },
      {
        "id": 50906,
        "about": "詹金",
        "title": "闲话·关于詹金",
        "content": "哎呀，可爱的小老鼠蹿过去了……我听说，老鼠可是喜欢偷腥的动物呢，可惜，这一只还太小，尚在襁褓之中……"
      },
      {
        "id": 90358,
        "about": "詹金",
        "title": "闲话·关于詹金",
        "content": "那位神偷告诉我，她可以教会我最厉害的街头生存技巧，只需要付给她五百雷欧坊……我被骗了？不，我认为这是很值得学习的知识，这正是我和波吕克斯所缺少的……是钱的问题？我明白了，那么，我去找她商量，付给她四百五十雷欧坊如何？"
      },
      {
        "id": 117791,
        "about": "詹金",
        "title": "闲话·关于詹金",
        "content": "我承认她偷东西的本事有几分厉害，但淑女还用不上这样卑鄙的伎俩，我想要的东西，让大家「自愿」给我不就好了？"
      }
    ],
    "图鲁": [
      {
        "id": 4909,
        "about": "图鲁",
        "title": "闲话·关于图鲁",
        "content": "可恶，他明明也是小孩子，你们怎么都那么尊敬他！拿出同样的态度来对待本小姐，知道吗！"
      },
      {
        "id": 4946,
        "about": "图鲁",
        "title": "闲话·关于过去",
        "content": "我不是什么重要之人，不过是众多信徒中渺小的一滴……只要能为那位大人效力，引得其侧目，我愿献上我所有的精与神……"
      },
      {
        "id": 5718,
        "about": "图鲁",
        "title": "闲话·关于深海血脉",
        "content": "那就是回归本源的形态吗……不，和我想象中有些不一样。不过，要是我也能变成那个样子就好了。"
      },
      {
        "id": 6361,
        "about": "图鲁",
        "title": "闲话·关于图鲁",
        "content": "你怎么会把他召唤出来！那个没用的瞌睡虫！自甘堕落、不思进取……枉我曾对他寄予厚望！我们走！我不想见到这个家伙！"
      },
      {
        "id": 6369,
        "about": "图鲁",
        "title": "闲话·关于图鲁",
        "content": "那便是祂的切片吗？不错，倒是很有王之威仪。"
      },
      {
        "id": 6703,
        "about": "图鲁",
        "title": "闲话·关于图鲁",
        "content": "啊啊……他的光辉是如此灼热闪耀，不容忽视，是愚昧的狂热遮住了我的感官……不，我不能为我的愚笨找任何理由……"
      },
      {
        "id": 117806,
        "about": "图鲁",
        "title": "闲话·关于图鲁",
        "content": "你别看他长得像小孩，实际上岁数大得早就能入土了，不要说糖果，就是任何活人喜欢的东西他也不会感兴趣的。所以，要送给他的那份糖，不如统统送给我，我才是最不会辜负它们的人。"
      }
    ],
    "温柯尔": [
      {
        "id": 4929,
        "about": "温柯尔",
        "title": "闲话·关于温柯尔",
        "content": "温柯尔的原生种族拥有进入生物大脑的能力，与我相融的外域意志为此十分忌惮她。不过，她现在也只是个被躯壳束缚住的可怜灵魂罢了。"
      },
      {
        "id": 5631,
        "about": "温柯尔",
        "title": "闲话·关于温柯尔",
        "content": "为了在艾瑞卡「睡觉」时研究这具身体的内部构造，温柯尔要求我夜晚去她的办公室休眠。"
      },
      {
        "id": 5698,
        "about": "温柯尔",
        "title": "闲话·关于温柯尔",
        "content": "她在夜里时常会待在我附近，是我这颗头颅太注目了吗？"
      },
      {
        "id": 5929,
        "about": "温柯尔",
        "title": "闲话·关于星外之人",
        "content": "那些家伙的气息很陌生，他们不是这颗星球自然诞生的生命吧。"
      },
      {
        "id": 5976,
        "about": "温柯尔",
        "title": "闲话·关于温柯尔",
        "content": "温柯尔小姐和我一样，故乡都不在这颗星球上……除了汀克特以外，我的家乡没有任何值得我留恋的。不知道温柯尔小姐对她的故乡，怀有怎样的感情呢？"
      },
      {
        "id": 6344,
        "about": "温柯尔",
        "title": "闲话·关于温柯尔",
        "content": "那位黑眼圈很重的小姐，曾向我咨询「永远活在阳光下」的方法……的确，只要在两个世界中往返迁移就好了。可是，她无论都不肯踏入维度隧道呢……真伤脑筋。"
      }
    ],
    "弥利亚姆": [
      {
        "id": 4949,
        "about": "弥利亚姆",
        "title": "闲话·关于蹈海者",
        "content": "……罢了，只要不用那些狂热的祭拜叨扰余，与他们共处一室也未尝不可。"
      },
      {
        "id": 5341,
        "about": "弥利亚姆",
        "title": "闲话·关于弥利亚姆",
        "content": "为大多数人担任护航的庇佑者都没有什么区别，但那个女人除外。如果可以，请为我安排其他航线吧。"
      },
      {
        "id": 5629,
        "about": "弥利亚姆",
        "title": "闲话·关于弥利亚姆",
        "content": "会独自航船漂洋过海的女人，除了女神，还有女疯子。当初我把弥利亚姆认作女神，真是天大的错误。"
      },
      {
        "id": 5727,
        "about": "弥利亚姆",
        "title": "闲话·关于弥利亚姆",
        "content": "她也是个可怜人，终将被命运蹂躏。因为，祂真正降生之刻，就是我将死亡赐予她之时。"
      },
      {
        "id": 6259,
        "about": "弥利亚姆",
        "title": "闲话·关于弥利亚姆",
        "content": "你这家伙，怎么会放那种女人进来！给本小姐划定禁区！别让她靠近本小姐周围五十步内！"
      },
      {
        "id": 95053,
        "about": "弥利亚姆",
        "title": "闲话：关于弥利亚姆",
        "content": "一位过于狂热的信者，或许在世人眼中只是不可理喻的疯子，虽然她也曾走入歧途，但这样为神明付出一切的决心，却是绝大多数庸人都做不到的坚毅，我对于她么……只有些同类相见的悲伤罢了。"
      }
    ],
    "艾继丝": [
      {
        "id": 4964,
        "about": "艾继丝",
        "title": "闲话·关于艾继丝",
        "content": "究竟是怎样不负责的父母，才会以女妖之盾命名自己的女儿？你说那孩子没有父母？嗯……我们这段对话，没必要让她知道。"
      },
      {
        "id": 5915,
        "about": "艾继丝",
        "title": "闲话·关于艾继丝",
        "content": "那傻妞怎么一看见我就跑？下次我要踩着她的毛线，看她能往哪跑。"
      },
      {
        "id": 6145,
        "about": "艾继丝",
        "title": "闲话·关于神之血脉",
        "content": "这女孩身上流淌着的，毫无疑问是余之血脉……不，余的年纪还不足以留下子嗣。但是，她的力量确实与余同宗。"
      },
      {
        "id": 6555,
        "about": "艾继丝",
        "title": "闲话·关于孩子们",
        "content": "你们几个，每次都来看魔术秀，不会腻吗？要乖乖坐好哦？再跑到舞台上的话，我就把你们丢到异次元空间里去！"
      },
      {
        "id": 81165,
        "about": "艾继丝",
        "title": "闲话·关于艾继丝",
        "content": "如今的艾继丝看起来开朗了许多。当然，如果我的小小客人有需要，我很乐意提供帮助。我是指，真正的帮助。"
      },
      {
        "id": 95073,
        "about": "艾继丝",
        "title": "闲话：关于艾继丝和詹金",
        "content": "不幸的孩子，不过她既已投身于追随您的事业，便一定能得到最终的救赎。不过她那个猴子一样的朋友为何也得到了您的垂怜？那个邪恶的小孩甚至偷走了我祈祷的法器！她的灵魂中一定隐藏着洪水一般的罪孽，真是不敬！不敬！"
      }
    ],
    "达芙黛尔": [
      {
        "id": 5159,
        "about": "达芙黛尔",
        "title": "闲话·关于达芙黛尔",
        "content": "不要让那个戴紫色宽檐帽的女人靠近舞台！没有为什么，只要你不想让礼帽里流出黏糊糊的灰质的话，就别让她过来！"
      },
      {
        "id": 5791,
        "about": "达芙黛尔",
        "title": "闲话·关于达芙黛尔",
        "content": "我向您发誓，那位店主绝对在枫丹白露的沙龙中露过脸……原来如此，从那时起，她就是如此模样吗。不知道从她手中，能换得多少密辛呢？"
      },
      {
        "id": 6192,
        "about": "达芙黛尔",
        "title": "闲话·关于达芙黛尔",
        "content": "嗯，莉莉认得她。母亲不在的时候，莉莉就住在她家里。"
      },
      {
        "id": 6579,
        "about": "达芙黛尔",
        "title": "闲话·关于达芙黛尔",
        "content": "我想要一盏不会熄灭的灯，她居然说什么，用“没有翅膀却会飞的水螅的标本”来交换。我上哪找这么怪异的物种啊！"
      },
      {
        "id": 90339,
        "about": "达芙黛尔",
        "title": "闲话·关于达芙黛尔",
        "content": "能够满足任何愿望的商店，应有尽有的商品，真让人敬而远之……不，我没有质疑那位女士的力量，但，“想要拥有一样东西，就要付出相应的价格”，这样的道理，我和波吕克斯已经体会了太多次。"
      }
    ],
    "阿格里帕": [
      {
        "id": 5448,
        "about": "阿格里帕",
        "title": "闲话·关于阿格里帕",
        "content": "阿格里帕？不好意思，我亲手送走的人太多了，他们大多面目模糊，没有什么值得铭记的对手。"
      },
      {
        "id": 5809,
        "about": "阿格里帕",
        "title": "闲话·关于阿格里帕",
        "content": "嗯……阿格里帕也有很多伙伴呢，但是大家看起来都很怕她的样子。难不成，她会抢伙伴们的东西吃？"
      },
      {
        "id": 5892,
        "about": "阿格里帕",
        "title": "闲话·关于阿格里帕",
        "content": "那个干瘪的重瞳女人，闻起来和斯巴达臭虫如出一辙。"
      },
      {
        "id": 6197,
        "about": "阿格里帕",
        "title": "闲话·关于阿格里帕",
        "content": "什么角斗士的主人，不过是低劣的虫豸罢了。"
      },
      {
        "id": 50908,
        "about": "阿格里帕",
        "title": "闲话·关于阿格里帕",
        "content": "蜘蛛啊……蜘蛛。嗯~我喜欢蜘蛛，他们密密麻麻降生的瞬间就获得了行走的力量，这种繁殖和生存能力可真是让人羡慕……"
      }
    ],
    "萨尔瓦多": [
      {
        "id": 5802,
        "about": "萨尔瓦多",
        "title": "闲话·关于萨尔瓦多",
        "content": "我不擅长与神职者相处。他们无趣又古板，还将腰带交给了他们敬爱的「神」，真可惜，萨尔瓦多先生明明闻起来是如此的甜美……"
      },
      {
        "id": 5920,
        "about": "萨尔瓦多",
        "title": "闲话·关于萨尔瓦多",
        "content": "那位圣父没办法拯救所有人。他也许能帮助一个倒霉鬼，但不能把所有人拖出泥沼……我很期待他，期待他信仰的崩塌。"
      },
      {
        "id": 6306,
        "about": "萨尔瓦多",
        "title": "闲话·关于萨尔瓦多",
        "content": "我和那个男人聊不来的啦。人生哪有那么多罪啊罚啊的，及时行乐才比较要紧吧？"
      },
      {
        "id": 95077,
        "about": "萨尔瓦多",
        "title": "闲话：关于萨尔瓦多",
        "content": "那位神父盲目的救赎实在是不可取的愚行，神的福音自然只能赐予虔诚的义人，若连神的使徒都没有一双洞察的慧眼，使不加悔改、满身罪孽的恶徒获得奖赏，污染了神纯净的国度，这岂不是对神明与那些义人的背叛吗？"
      },
      {
        "id": 123797,
        "about": "萨尔瓦多",
        "title": "闲话：关于萨尔瓦多",
        "content": "为了别人而牺牲自己，真是愚蠢又令人生气的想法。没有谁可以这样要求别人，就算是神也不行。"
      }
    ],
    "索蕾尔": [
      {
        "id": 5101,
        "about": "索蕾尔",
        "title": "闲话·关于索蕾尔",
        "content": "红夫人和我侍奉过的任何主君都不一样……不，我并不是讨厌她，只是、只是有些难以招架……"
      },
      {
        "id": 5654,
        "about": "索蕾尔",
        "title": "闲话·关于索蕾尔",
        "content": "守密人，我必须跟你谈谈。在我们取得最终胜利之前，某些人不应当如此奢靡浪费。要知道，我不是为那种人的贵族生活而奋战的。"
      },
      {
        "id": 56320,
        "about": "索蕾尔",
        "title": "闲话·关于索蕾尔",
        "content": "那位红夫人可真美。她的强大与自信，她面对命运的优雅微笑，她那如同红蔷薇般旺盛又决绝的生命力，都让我无比羡慕……"
      },
      {
        "id": 126956,
        "about": "索蕾尔",
        "title": "闲话：关于索蕾尔",
        "content": "那位红夫人，曾给妾身发过几回沙龙请柬。"
      }
    ],
    "珈伦": [
      {
        "id": 5575,
        "about": "珈伦",
        "title": "闲话·关于珈伦",
        "content": "一名优秀的侍女能为沙龙增色不少，但蓝绿色的侍女……容我再斟酌一番……"
      },
      {
        "id": 5688,
        "about": "珈伦",
        "title": "闲话·关于珈伦",
        "content": "我好几次拒绝了女仆小姐的宴会邀请，她看起来有些失落……但相比起玩乐，自然是主君的安危更为重要！"
      },
      {
        "id": 90346,
        "about": "珈伦",
        "title": "闲话·关于珈伦",
        "content": "现在想来，在提灯时的那些侍女其实与我和波吕克斯没有什么分别，我们都是戴着一条条锁链在生活，而她们对此始终顺从而忍耐。不过那位绿色的侍女似乎不太一样，她……非常有活力，好像天生就喜爱做这些，或许她已经拥有了最宝贵的自由吧。"
      },
      {
        "id": 123805,
        "about": "珈伦",
        "title": "闲话：关于珈伦",
        "content": "女仆啊，我也做过，找个时间给她看看我开发的、使用吸尘器战斗的办法！"
      }
    ],
    "莉莉": [
      {
        "id": 5811,
        "about": "莉莉",
        "title": "闲话·关于莉莉",
        "content": "怯懦的家伙，明明拥有与我相似的强大力量，却如此压制自己，这和自愿戴上项圈有什么区别！"
      },
      {
        "id": 6006,
        "about": "莉莉",
        "title": "闲话·关于莉莉",
        "content": "我能感觉到，那个小女孩拥有和我相似的力量。她还没完全理解这份力量的强大，看在你的份上，我会适当训练她的。"
      },
      {
        "id": 117831,
        "about": "莉莉",
        "title": "闲话·关于莉莉",
        "content": "那个孩子听话得有点吓人了，只要你向她要糖，她就会给，甚至自己一颗也没留下，让人还怪不好意思的……咳咳，我是说，既然她这么识趣，仁慈的女巫当然会给她留下一些作为赏赐啦。"
      },
      {
        "id": 126981,
        "about": "莉莉",
        "title": "闲话：关于莉莉",
        "content": "妾身也有过这么一个漂亮的、唯唯诺诺的小姑娘。"
      }
    ],
    "泰旖丝": [
      {
        "id": 5950,
        "about": "泰旖丝",
        "title": "闲话·关于泰旖丝",
        "content": "那女人的愿望真是令人发笑。没有东西能在湮灭后存活，就算是「神」也一样。"
      },
      {
        "id": 6530,
        "about": "泰旖丝",
        "title": "闲话·关于泰旖丝",
        "content": "你还是别和泰旖丝小姐走得太近……不，我没有吃醋，我只是怕有人会上女人的当。"
      },
      {
        "id": 67276,
        "about": "泰旖丝",
        "title": "闲话·关于欲之质体",
        "content": "欲之质体提芙蕾耶索德，她亦求取了自己的存续之道。在未知面前，无人得以判断手段的崇高与卑劣。"
      },
      {
        "id": 95433,
        "about": "泰旖丝",
        "title": "闲话：关于泰旖丝",
        "content": "传说中的亚兰女王，伟大的欲之质体提芙蕾耶索德，我曾在追杀N的时候见过她一面。虽然我不认可她所做的那些事情，但平心而论，若那是我能找到的，让大家从「祂」的瞥视中存活下来的唯一方式……我也会做出相同的选择。从这个角度上来讲，我和她并没有什么区别。"
      }
    ],
    "朵尔": [
      {
        "id": 4966,
        "about": "朵尔",
        "title": "闲话·关于朵尔",
        "content": "朵尔在的时候，调查员们的效率普遍提高78.312%，相应的也有更多人陷入情绪低潮。引用她的一句话：有的人如果能管好嘴，世界运转会更加流畅。"
      },
      {
        "id": 6722,
        "about": "朵尔",
        "title": "闲话·关于朵尔",
        "content": "朵尔小姐说，我可以像她一样通过抛弃肉体来暂时躲避融蚀……做不到做不到做不到，进行手术时会失去意识，黑暗会趁虚而入……"
      },
      {
        "id": 129659,
        "about": "朵尔",
        "title": "闲话：关于朵尔",
        "content": "冷冰冰，可怕，莫丝，躲起来！"
      }
    ],
    "汀克特": [
      {
        "id": 4980,
        "about": "汀克特",
        "title": "闲话·关于汀克特",
        "content": "汀克特……听到她哀婉的歌声，就会忍不住想要起舞……"
      },
      {
        "id": 6710,
        "about": "汀克特",
        "title": "闲话·关于汀克特",
        "content": "我在星间漂流的日子里，无数次梦到这一天……谢谢你，让我和汀克特团聚。"
      },
      {
        "id": 56328,
        "about": "汀克特",
        "title": "闲话·关于汀克特",
        "content": "假如诗歌是为赞颂美而存在的，那她的存在就像是诗歌本身。当她开始歌唱的时候，我突然就明白了前辈们形容的，夜莺般的歌喉……"
      }
    ],
    "戈利亚": [
      {
        "id": 5563,
        "about": "戈利亚",
        "title": "闲话·关于戈利亚",
        "content": "哎呀，世间怎么会有这样傲慢的客人，想要「世界上最好用的武器」？我告诉他，需要用浸满仇恨的头颅来换，他就悻悻地走了……"
      },
      {
        "id": 6375,
        "about": "戈利亚",
        "title": "闲话·关于戈利亚",
        "content": "他是个好用的战士，我曾将他视作“同伴”……什么，你说，我对“同伴”的定义有问题？愿闻其详。"
      },
      {
        "id": 129676,
        "about": "戈利亚",
        "title": "闲话：关于戈利亚",
        "content": "打架！"
      }
    ],
    "菲茵特": [
      {
        "id": 5649,
        "about": "菲茵特",
        "title": "闲话·关于菲茵特",
        "content": "这是我的签名海报，皮克曼先生为我绘制的。我把它赠与你。"
      },
      {
        "id": 6127,
        "about": "菲茵特",
        "title": "闲话·关于菲茵特",
        "content": "没想到竟能在此处重逢……不知道那之后姐姐过着怎样的生活。无论怎样询问，她都只说并无大碍……抱歉，还得感谢您让我们姐妹二人团聚。"
      },
      {
        "id": 6206,
        "about": "菲茵特",
        "title": "闲话·关于菲茵特",
        "content": "我知道那孩子，她偶尔会远远地站在场外观看演出。她不过来也好，不然，这些小观众们可要“身心俱疲”啦！"
      }
    ],
    "奥瑞塔": [
      {
        "id": 5782,
        "about": "奥瑞塔",
        "title": "闲话·关于奥瑞塔",
        "content": "我一直不好意思告诉奥瑞塔，我并没有她想象中那么年幼……能替我劝劝她，不要再叫我“妹妹”了吗？"
      },
      {
        "id": 6470,
        "about": "奥瑞塔",
        "title": "闲话·关于奥瑞塔",
        "content": "皮克曼与我正在合作一些有趣的装置艺术，探讨如何通过解构视觉原始主义重构抽象表象主义......咦，奥瑞塔怎么晕倒了？"
      },
      {
        "id": 81140,
        "about": "奥瑞塔",
        "title": "闲话·关于奥瑞塔",
        "content": "虽然这么说有些失礼，但与那孩子谈话只会让我觉得无聊——你永远只能看到一种表情，那就是笑容。"
      }
    ],
    "诺缔拉": [
      {
        "id": 6331,
        "about": "诺缔拉",
        "title": "闲话·关于诺缔拉",
        "content": "每隔一段时间，那个骑摩托的小姑娘都会帮我进行义肢保养。不过，最近检修的频率是不是有些过高了？"
      },
      {
        "id": 6347,
        "about": "诺缔拉",
        "title": "闲话·关于诺缔拉",
        "content": "什么叫我拿的，你可别冤枉好人！她那些破螺丝不见的时候我可是——布朗别！……嘿嘿，你就当什么也没看见吧？"
      },
      {
        "id": 129693,
        "about": "诺缔拉",
        "title": "闲话：关于诺缔拉",
        "content": "诺缔拉，想见。诶，诺缔拉，莫丝，莫丝！"
      }
    ],
    "法洛思": [
      {
        "id": 5018,
        "about": "法洛思",
        "title": "闲话·关于法洛思",
        "content": "那位像是灯塔一样的小姐……在永夜的航行中，要是能够看到她那样耀眼的光芒，或许我就不会陷入迷失了吧……"
      },
      {
        "id": 5449,
        "about": "法洛思",
        "title": "闲话·关于法洛思",
        "content": "危险的船员……不，只是从航行安全的角度出发……"
      }
    ],
    "艾瑞卡": [
      {
        "id": 5271,
        "about": "艾瑞卡",
        "title": "闲话·关于艾瑞卡",
        "content": "希望在我们进行这场对话时，她的运行不要出错。我可爱又可憎的助手啊，已经没有多余的实验室供她爆破了。"
      },
      {
        "id": 50912,
        "about": "艾瑞卡",
        "title": "闲话·关于艾瑞卡",
        "content": "有意识之物，就有欲望，就算是机械的生物也不会例外吧？"
      }
    ],
    "旺达": [
      {
        "id": 5294,
        "about": "旺达",
        "title": "闲话·关于旺达",
        "content": "我和那家伙可不一样，她供应的只有充满敌意的战栗和恐惧，我给予的可是肌肤相亲、甜蜜滚烫的疼痛与爱哦？"
      },
      {
        "id": 5326,
        "about": "旺达",
        "title": "闲话·关于旺达",
        "content": "我还挺喜欢那女人的，我们有那个，那个什么……对，共同语言！"
      }
    ],
    "希洛": [
      {
        "id": 5350,
        "about": "希洛",
        "title": "闲话·关于希洛",
        "content": "那个大姐姐，总是凶凶地瞪着我。可不知道为什么，我总有种亲切的感觉。是因为像母亲？"
      },
      {
        "id": 5789,
        "about": "希洛",
        "title": "闲话·关于@2",
        "content": "我在走廊里遇到了一些让我感觉不妙的人。或许受局势所迫，你必须要和她们协同作战，但请时刻保持警惕。比战争更残酷的东西唯有人心，最可怕的背叛往往来源于内部。"
      }
    ],
    "尤乌哈希": [
      {
        "id": 5392,
        "about": "尤乌哈希",
        "title": "闲话·关于尤乌哈希",
        "content": "尤乌哈希......他有点像我的哥哥，总让我想起那些阴暗、冷淡而失眠的日子。"
      },
      {
        "id": 6757,
        "about": "尤乌哈希",
        "title": "闲话·关于尤乌哈希",
        "content": "尤乌哈希……他是很特别。你以为我家风光的日子是怎么来的？全靠他在竞技场像疯狗一样杀人。他才是我家最大的摇钱树。"
      }
    ],
    "希莱斯特": [
      {
        "id": 5816,
        "about": "希莱斯特",
        "title": "闲话·关于希莱斯特",
        "content": "我很向往那个人，洁白高雅如同百合花的航海神明……您说这样的她，也无法掌控自己的命运，最终沉没于海底吗？这，实在难以想象……"
      },
      {
        "id": 84225,
        "about": "希莱斯特",
        "title": "闲话·关于希莱斯特",
        "content": "必要时刻，学过轮机舱协作的领航员也能充当舵手，但为了确保船只安全，我还是希望能够将这项任务交给擅长的人。"
      }
    ],
    "卡茜亚": [
      {
        "id": 6016,
        "about": "卡茜亚",
        "title": "闲话·关于卡茜亚",
        "content": "卡茜亚好厉害！她能咻——地一下变出小兔子！"
      },
      {
        "id": 56313,
        "about": "卡茜亚",
        "title": "闲话·关于卡茜亚",
        "content": "我偷偷去看了卡茜亚小姐的魔术。她的表演带给了观众很多的快乐，可我却总是将悲伤带给大家……您说，眼泪与笑容，是同样珍贵的事物？或许……"
      }
    ],
    "雷娅": [
      {
        "id": 6603,
        "about": "雷娅",
        "title": "闲话·关于雷娅",
        "content": "雷娅是谁？哦，那个求我揍她的女人。哈哈，有点意思......这里也没那么无聊嘛。"
      },
      {
        "id": 96386,
        "about": "雷娅",
        "title": "闲话·关于雷娅",
        "content": "那位小姐的热情虽然十分令人动容，但她的气味闻起来，有着某种发酵过头的潮湿味道。哪怕是她不住恳求着我品尝一下，这也实在不符合我的口味，真叫人为难。"
      }
    ],
    "凯刻斯": [
      {
        "id": 6611,
        "about": "凯刻斯",
        "title": "闲话·关于凯刻斯",
        "content": "哎呀，本店售出的商品概不退换哦？想要下潜至深海，的确是需要潜水艇的吧？"
      },
      {
        "id": 6681,
        "about": "凯刻斯",
        "title": "闲话·关于凯刻斯",
        "content": "刚才走过的，是深海的混种么？唔......看看这挺直的脊梁吧，今夜我就要见到他匍匐跪地的模样。"
      }
    ],
    "拉蒙娜": [
      {
        "id": 50910,
        "about": "拉蒙娜",
        "title": "闲话·关于塔薇",
        "content": "哎呀，不得不承认我输给她一次了呢……好在，被她选择的您，也会饮下树的乳汁，将我的血与种带往新的世界吧？"
      },
      {
        "id": 67305,
        "about": "拉蒙娜",
        "title": "闲话·关于拉蒙娜",
        "content": "那个孩子，因我的意识碎片，已然承受了太多她本不应承受的。好在她的灵魂仍如流动的银一般澄澈……"
      }
    ],
    "莉兹": [
      {
        "id": 56329,
        "about": "莉兹",
        "title": "闲话·关于莉兹",
        "content": "那位美貌的舞者……她身上碧绿色的火焰，让人忍不住想要去触碰，即便被焚烧殆尽也无所谓……"
      },
      {
        "id": 61004,
        "about": "莉兹",
        "title": "闲话·关于莉兹",
        "content": "那位绿色的舞者，有着足以成为宫廷舞团首席的优雅姿态。"
      }
    ],
    "24": [
      {
        "id": 5410,
        "about": "24",
        "title": "闲话·关于「24」",
        "content": "梅森……不，这样就很好，至少我们又能在一起了，「24」。"
      }
    ],
    "潘狄娅": [
      {
        "id": 5991,
        "about": "潘狄娅",
        "title": "闲话·关于潘狄娅",
        "content": "潘狄娅......她管这也叫调教？哈哈......容我先笑一会。人类终归还是太心慈手软了一些，做什么看起来都像过家家。"
      }
    ],
    "奥吉尔": [
      {
        "id": 6109,
        "about": "奥吉尔",
        "title": "闲话·关于奥吉尔",
        "content": "大学里怎么还有这么可爱的孩子呀~我刚和他说“要不要来当我的奴隶”，他就涨红了脸，吞吞吐吐地念叨什么“我已经是守密人的骑士了”……"
      }
    ],
    "萝坦": [
      {
        "id": 6639,
        "about": "萝坦",
        "title": "闲话·关于萝坦",
        "content": "我能感觉到那位小姐的敌意，是我对您的爱招致嫉妒了吧……您瞧，那只大翅鲸的嘴都妒忌地张开了呢。"
      }
    ],
    "莱克": [
      {
        "id": 50901,
        "about": "莱克",
        "title": "闲话·关于莱克",
        "content": "狼的小哥啊……他和那位N之间，可有些说不清道不明的关系……"
      }
    ],
    "艾尔瓦": [
      {
        "id": 50903,
        "about": "艾尔瓦",
        "title": "闲话·关于艾尔瓦",
        "content": "那是个过分勤勉和谨慎的孩子，我当然不会苛责她了~如果没有她，随心所欲的种群早就毁灭于变迁之中了吧？"
      }
    ],
    "宁菲亚": [
      {
        "id": 56324,
        "about": "宁菲亚",
        "title": "闲话·关于宁菲亚",
        "content": "每次看到宁菲亚小姐，我都会想起那幅画着睡莲的画。她的身上，有着睡莲般宁静的苦涩与清香……不知道她眼中的世界会是什么样子呢？"
      }
    ],
    "环行·拉蒙娜": [
      {
        "id": 67298,
        "about": "环行·拉蒙娜",
        "title": "闲话·关于环行拉蒙娜",
        "content": "她亦是我的碎片之一，来自其他维度，一个已经永恒湮灭的世界。很遗憾，她虽然掌握了时间回溯的方式，却未能理解超越时空的真谛，只能在苦痛中一次次沦陷。这是我的错误。"
      }
    ],
    "法洛斯": [
      {
        "id": 84199,
        "about": "法洛斯",
        "title": "闲话·关于法洛思",
        "content": "灯塔系统能够极大减轻领航的压力，而她的灯光尤其明亮，我很乐意与法洛思一起出航。"
      }
    ],
    "杜勒赛因": [
      {
        "id": 90345,
        "about": "杜勒赛因",
        "title": "闲话·关于杜勒赛因",
        "content": "烹饪美食的大师么……制作食物的知识果然也是非常必要的，虽然我对进食的要求并不高，但波吕克斯实在太挑嘴了。看来应该找个时间去认真请教一下……不要去？为什么，可是那位先生制作的食物看起来都十分美味？"
      }
    ],
    "波吕克斯": [
      {
        "id": 90365,
        "about": "波吕克斯",
        "title": "闲话·关于波吕克斯",
        "content": "波吕克斯他……虽然被提灯灌输了很多不好的想法，但他的本心是不坏的。他只是迫切地想要得到提灯的认可、教众的认可，以至于过分地在乎他们的需求。与其说他太过自我，不如说，他一直害怕失去那份“自我”。"
      }
    ],
    "卡斯托尔": [
      {
        "id": 95055,
        "about": "卡斯托尔",
        "title": "闲话：关于卡斯托尔",
        "content": "哈……过去这么久，他还是一点都没变。儿时的我或许从没想到，有一天我会伤害、亏欠哥哥如此之多，多到令我自惭形秽，即便这悲剧的命运并不受我们任何一人控制。我们曾经历了那么多分离，但，既然我已经回来了，从今往后，不会再有任何事能将我们分开，哪怕是死亡。"
      }
    ],
    "皮克曼": [
      {
        "id": 96367,
        "about": "皮克曼",
        "title": "闲话·关于皮克曼",
        "content": "和我一样，皮克曼也在追求着永恒的艺术，我们本应成为更好的朋友。可他却认为进食是一种破坏永恒的行为，这种艺术理念实在过于狭隘。"
      }
    ],
    "珊": [
      {
        "id": 100345,
        "about": "珊",
        "title": "闲话：关于珊",
        "content": "虽然我觉得雕刻这种艺术形式有些过于生硬古板，但那位叫做珊的雕刻家，她的刻刀能够拥有超越这个艺术形式所能承载的表达力……真是一位难得的天才！"
      }
    ],
    "哈姆林": [
      {
        "id": 100372,
        "about": "哈姆林",
        "title": "闲话：关于哈姆林",
        "content": "我信奉的艺术理念是疯狂、躁动不安的，哈姆林的音乐完全不一样，严谨得像是那些死气沉沉的公墓墓碑。但不知道为什么，我总能在那些整齐的音符里，看到宇宙深处最强烈的混乱……"
      }
    ]
  }
}