{
  "collected_at": "2026-06-30T16:22:05.225565+00:00",
  "source": "reddit",
  "data_layer": "output",
  "item_count": 22,
  "items": [
    {
      "source": "reddit",
      "time": "2026-06-30T10:56:10+00:00",
      "lang": "en",
      "title": "Evil Aigis",
      "summary": "&#32; submitted by &#32;  /u/CaptainFantom   [link] &#32; [comments]",
      "url": "https://old.reddit.com/r/Morimens/comments/1ujlwwy/evil_aigis/",
      "author": "/u/CaptainFantom",
      "engagement": 0,
      "media_url": "https://preview.redd.it/bt4vm92zheah1.jpeg?width=640&amp;crop=smart&amp;auto=webp&amp;s=22625fc55b446426daa4a7c27afa4ed806e08309",
      "content_type": "image",
      "metadata": {
        "via": "rss"
      }
    },
    {
      "source": "reddit",
      "time": "2026-06-30T06:57:20+00:00",
      "lang": "en",
      "title": "Wow....",
      "summary": "Took me like 50 pulls jdhahhshaj good thing I got his wod in 10 pulls because im saving for gtulu 😢  &#32; submitted by &#32;  /u/jadhanshsnajsakak   [link] &#32; [comments]",
      "url": "https://old.reddit.com/r/Morimens/comments/1ujht7w/wow/",
      "author": "/u/jadhanshsnajsakak",
      "engagement": 0,
      "media_url": "https://preview.redd.it/yejniodkbdah1.jpeg?width=640&amp;crop=smart&amp;auto=webp&amp;s=449c76e0ed2144a5e1a2f2d9c88dde3968d4a887",
      "content_type": "image",
      "metadata": {
        "via": "rss"
      }
    },
    {
      "source": "reddit",
      "time": "2026-06-30T14:40:43+00:00",
      "lang": "en",
      "title": "I GOT THIS MOTHERFUCKER IN A SINGLE PULL!!!!!HOLY SHIT",
      "summary": "I legit logged on and was like yay cool new character I&#39;ll get one copy ig, claimed the single seasonal pull (Mythag gifts) and rolled, obviously i skipped the animation and i was jumpscared by this GLORIOUS JUICY GRANDPA HOLY SHIT I FINALLY FOUND A GAME THAT LOVES ME BACK!!!!!!! Ps: Yes i genuinely don&#39;t know how to play this man, for the upcoming banners should i go for corpo for this man or go all in for his dupes?   &#32; submitted by &#32;  /u/yagamLight2483   [link] &#32; [comments]",
      "url": "https://old.reddit.com/r/Morimens/comments/1ujr43d/i_got_this_motherfucker_in_a_single_pullholy_shit/",
      "author": "/u/yagamLight2483",
      "engagement": 0,
      "media_url": "https://preview.redd.it/gyyrene7mfah1.jpg?width=140&amp;height=63&amp;auto=webp&amp;s=23f7ef2bdc4236a2f8f4b1660d024cdb95cd0ecd",
      "content_type": "image",
      "metadata": {
        "via": "rss"
      }
    },
    {
      "source": "reddit",
      "time": "2026-06-30T07:39:21+00:00",
      "lang": "en",
      "title": "The guy that introduced me into the game made a guide...",
      "summary": "Absolute cinema sir Pseychie  &#32; submitted by &#32;  /u/izy911   [link] &#32; [comments]",
      "url": "https://old.reddit.com/r/Morimens/comments/1ujijp1/the_guy_that_introduced_me_into_the_game_made_a/",
      "author": "/u/izy911",
      "engagement": 0,
      "media_url": "https://external-preview.redd.it/_xvMQzj8eeXa1gzcXnnHBBp5pkEIQTqDubpgt5dKm1I.jpeg?width=320&amp;crop=smart&amp;auto=webp&amp;s=0f79b2a639789b7b1e206a4e129110dead6f30e7",
      "content_type": "image",
      "metadata": {
        "via": "rss"
      }
    },
    {
      "source": "reddit",
      "time": "2026-06-30T12:56:58+00:00",
      "lang": "en",
      "title": "Pickman & Pontos - Continuous 0 Cost Gaunt - Is this a bug?",
      "summary": "Pickman Exalt with devour gets the next command card -2 cost, and somehow Pontos Gaunt cards get that effect all the time till the other card is played.  I wonder if this is a bug.  &#32; submitted by &#32;  /u/blake8129   [link] &#32; [comments]",
      "url": "https://old.reddit.com/r/Morimens/comments/1ujohrt/pickman_pontos_continuous_0_cost_gaunt_is_this_a/",
      "author": "/u/blake8129",
      "engagement": 0,
      "media_url": "https://external-preview.redd.it/bXkzdmR3cWozZmFoMSIraxZnvOW6xIly82Fave5baFwGbvmU_5wkwyK6cnsL.png?width=640&amp;crop=smart&amp;auto=webp&amp;s=1a08b422fbf70273e006a9785aabab6ca6663128",
      "content_type": "image",
      "metadata": {
        "via": "rss"
      }
    },
    {
      "source": "reddit",
      "time": "2026-06-30T12:18:25+00:00",
      "lang": "en",
      "title": "Pontos X Saya actually works?",
      "summary": "Just tested whale Pontos with Saya and his dmg is insane! Some kills got stolen by Saya are totally fine since the corrosion value are just too much. I put some effort in the edit pls watch 🥉 Also the ytb link: Video   &#32; submitted by &#32;  /u/Champion_Frequent   [link] &#32; [comments]",
      "url": "https://old.reddit.com/r/Morimens/comments/1ujnlws/pontos_x_saya_actually_works/",
      "author": "/u/Champion_Frequent",
      "engagement": 0,
      "media_url": "https://external-preview.redd.it/bncweWJ2czZ3ZWFoMd11noxeF32c0-ubJRNaIr-gLZygAP5Q9eyNY7_37b5f.png?width=640&amp;crop=smart&amp;auto=webp&amp;s=e161ca1dae9cb264110349cb93aab63515e6dd86",
      "content_type": "image",
      "metadata": {
        "via": "rss"
      }
    },
    {
      "source": "reddit",
      "time": "2026-06-30T14:29:18+00:00",
      "lang": "en",
      "title": "teacher liz",
      "summary": "I made this with my very limited Photoshop skills idk if to even call it art but ig il post it here if any one wants to use it for some reason go ahead i have no problem with that  &#32; submitted by &#32;  /u/to_liz_or_not_to_liz   [link] &#32; [comments]",
      "url": "https://old.reddit.com/r/Morimens/comments/1ujqtgx/teacher_liz/",
      "author": "/u/to_liz_or_not_to_liz",
      "engagement": 0,
      "media_url": "https://preview.redd.it/ciodc1w4kfah1.jpeg?width=640&amp;crop=smart&amp;auto=webp&amp;s=3d70073a1303db01f1a0667fb025ed9f296f9647",
      "content_type": "image",
      "metadata": {
        "via": "rss"
      }
    },
    {
      "source": "reddit",
      "time": "2026-06-30T15:52:05+00:00",
      "lang": "en",
      "title": "D-tide teams question",
      "summary": "So these are the teams I made for d-tide based on my knowledge of the game, do they need some improvement? These are the for first five battle (so no the extra one&#39;s). I can complete d-tide but not the hard battles (except with pollution team)  &#32; submitted by &#32;  /u/Lightmay   [link] &#32; [comments]",
      "url": "https://old.reddit.com/r/Morimens/comments/1ujt0jl/dtide_teams_question/",
      "author": "/u/Lightmay",
      "engagement": 0,
      "media_url": "https://preview.redd.it/bu52seqaxfah1.jpg?width=140&amp;height=64&amp;auto=webp&amp;s=f16b5929736fb13c5dc3303afcf0609eb7c90084",
      "content_type": "image",
      "metadata": {
        "via": "rss"
      }
    },
    {
      "source": "reddit",
      "time": "2026-06-30T09:57:26+00:00",
      "lang": "en",
      "title": "I got Saya, is she playable?",
      "summary": "Hey, I came to the game for Saya but I missed her free copy and all the rewards from her event (Totally my fault. I started at the beginning of the event but I was completely lost and that discouraged me. I&#39;m only coming back now and I find out the event is over...). I managed to pull one copy and her card, but I heard she only becomes strong with three more copies (and her card too).Can I just use a copy or do I absolutely have to look for duplicates?  &#32; submitted by &#32;  /u/Ninoto   [link] &#32; [comments]",
      "url": "https://old.reddit.com/r/Morimens/comments/1ujkv0a/i_got_saya_is_she_playable/",
      "author": "/u/Ninoto",
      "engagement": 0,
      "media_url": "https://preview.redd.it/l61m6j0p7eah1.jpg?width=140&amp;height=63&amp;auto=webp&amp;s=e9f2f7082dbf36a9db13b39f5c8dbc03a2511e46",
      "content_type": "image",
      "metadata": {
        "via": "rss"
      }
    },
    {
      "source": "reddit",
      "time": "2026-06-30T08:15:35+00:00",
      "lang": "en",
      "title": "Finally beaten 5-11 Hard mode with 0 Gnosis",
      "summary": "I tried this boss many times with many combs the best I could get is getting 3 stars with like 2-3 gnosis  Even with 16 turns this time, that&#39;s a win  Got my 300 silver and that&#39;s what&#39;s important Lol This whole sub-chapter is made for vortice, everyone gets fortress☠️, even her as a keyflare bot made a good chunk of damage  Caecus and castor comb is probably one of the stronger combs in the game This team is insanely tanky.. Pretty high con team (my hp was like 2700) Lots of Shields from Corpo and castor and lots of healing from caecus (his +12 is really really good makes u get like 10-20k counter first or second turn) Idk how anyone beat this boss without the ultra turn his second phase and strength scaling is extremly annoying and that vulunerable   &#32; submitted by &#32;  /u/Youssefwell   [link] &#32; [comments]",
      "url": "https://old.reddit.com/r/Morimens/comments/1ujj5ue/finally_beaten_511_hard_mode_with_0_gnosis/",
      "author": "/u/Youssefwell",
      "engagement": 0,
      "media_url": "https://preview.redd.it/fc424jqhpdah1.jpeg?width=640&amp;crop=smart&amp;auto=webp&amp;s=550e467b917918e5cdf76517c6fc05be677defb2",
      "content_type": "image",
      "metadata": {
        "via": "rss"
      }
    },
    {
      "source": "reddit",
      "time": "2026-06-30T12:49:49+00:00",
      "lang": "en",
      "title": "Math is confusing",
      "summary": "Yeah, the math of this game is confusing. I&#39;m doing a (weak) aequor team with Vortice and Pontos since they both scale very well with tentacle damage (those two, Murphy and GMurphy, I&#39;d take tulu but i don&#39;t have him), but i realized something: how are tentacle damage calculated in the first place??? Once you have them adding damage is easy, but I can&#39;t find anywhere how the starting damage is calculated. Does anyone know?  &#32; submitted by &#32;  /u/Stewed_Pepper   [link] &#32; [comments]",
      "url": "https://old.reddit.com/r/Morimens/comments/1ujobrg/math_is_confusing/",
      "author": "/u/Stewed_Pepper",
      "engagement": 0,
      "metadata": {
        "via": "rss"
      }
    },
    {
      "source": "reddit",
      "time": "2026-06-30T07:07:25+00:00",
      "lang": "en",
      "title": "Where my AA vortice pontos??",
      "summary": "I blame you not so old young man 😡( pontos stole all the whales )  &#32; submitted by &#32;  /u/rajuzumaki   [link] &#32; [comments]",
      "url": "https://old.reddit.com/r/Morimens/comments/1ujhzrm/where_my_aa_vortice_pontos/",
      "author": "/u/rajuzumaki",
      "engagement": 0,
      "media_url": "https://preview.redd.it/089ow6xcddah1.jpeg?width=640&amp;crop=smart&amp;auto=webp&amp;s=e07376ea6b77861092107e51c9c0ef797c4a1ec4",
      "content_type": "image",
      "metadata": {
        "via": "rss"
      }
    },
    {
      "source": "reddit",
      "time": "2026-06-29T17:42:51+00:00",
      "lang": "en",
      "title": "What a great way to start the game",
      "summary": "&#32; submitted by &#32;  /u/Luuk_herrsonsWife   [link] &#32; [comments]",
      "url": "https://old.reddit.com/r/Morimens/comments/1uizezh/what_a_great_way_to_start_the_game/",
      "author": "/u/Luuk_herrsonsWife",
      "engagement": 0,
      "media_url": "https://preview.redd.it/g5babtftd9ah1.jpeg?width=640&amp;crop=smart&amp;auto=webp&amp;s=ec86a448b4e6cdfcd8743184c7cb58504bb6654d",
      "content_type": "image",
      "metadata": {
        "via": "rss"
      }
    },
    {
      "source": "reddit",
      "time": "2026-06-30T14:41:17+00:00",
      "lang": "en",
      "title": "Question regarding Faint exalt's DR gain",
      "summary": "[Solved] After such a long time, I&#39;ve finally gave Faint a try, and while really liking her (and regretting to to test her out sooner) I am an bit confused about the DR gain amount on her exalt. It starts with this gain 100+% DR, when you&#39;re under a certain threshhold, but somehow quckly gets to like a 4% DR increase. Can&#39;t find anything in her skills, abilities or where ever else which explains the decrease.  Is it tied towards the Arc 2 Faded Legacy ruleset change or and I just blind and there is actually an explanation for it in her kit somewhere?  &#32; submitted by &#32;  /u/-Esphir-   [link] &#32; [comments]",
      "url": "https://old.reddit.com/r/Morimens/comments/1ujr4lx/question_regarding_faint_exalts_dr_gain/",
      "author": "/u/-Esphir-",
      "engagement": 0,
      "metadata": {
        "via": "rss"
      }
    },
    {
      "source": "reddit",
      "time": "2026-06-30T04:52:43+00:00",
      "lang": "en",
      "title": "How to Pontos?",
      "summary": "I feel like I’m not understanding pontos i do his exalt and use guants but he is not killing anything 😂 Anyone has a good guide or pointers for how to build him and how to play him?   &#32; submitted by &#32;  /u/Outrageous_Finding71   [link] &#32; [comments]",
      "url": "https://old.reddit.com/r/Morimens/comments/1ujfj93/how_to_pontos/",
      "author": "/u/Outrageous_Finding71",
      "engagement": 0,
      "metadata": {
        "via": "rss"
      }
    },
    {
      "source": "reddit",
      "time": "2026-06-29T22:54:24+00:00",
      "lang": "en",
      "title": "Found the game thanks to Saya got any newbie advice?",
      "summary": "Welp, I&#39;m a fan of Saya no Uta, and i did hear there was a collab event in this game. I&#39;m a sucker for turn-based RPGs anyway, so I thought, why not give it a try. Any advice because there are quite a few menus and things that are pretty confusing.  &#32; submitted by &#32;  /u/LazyMakara   [link] &#32; [comments]",
      "url": "https://old.reddit.com/r/Morimens/comments/1uj7opu/found_the_game_thanks_to_saya_got_any_newbie/",
      "author": "/u/LazyMakara",
      "engagement": 0,
      "media_url": "https://preview.redd.it/xxw9zbz1xaah1.png?width=640&amp;crop=smart&amp;auto=webp&amp;s=000e4d1451cef3397773cb4b6e3bad6d45a0f47d",
      "content_type": "image",
      "metadata": {
        "via": "rss"
      }
    },
    {
      "source": "reddit",
      "time": "2026-06-30T09:48:59+00:00",
      "lang": "en",
      "title": "Saya's Rouse",
      "summary": "Hi, I&#39;m a relatively new player (joined bc of an ad featuring Salvador &amp; rejoined for Pontos) and was wondering if I&#39;m maybe not understanding correctly. Saya&#39;s Rouse states that when Crimson Furnace is used it causes her perception effect. Now if it wasn&#39;t obvious I run Salvador for.... reasons, but since he uses Crimson Furnace with his skills I assumed it would trigger off those, but i have yet to see it. So I was wondering if anyone knew for certain if it should, or if her Rouse is specified to active use of Furnace instead of skill interactions.  &#32; submitted by &#32;  /u/Adashi_McGay   [link] &#32; [comments]",
      "url": "https://old.reddit.com/r/Morimens/comments/1ujkptm/sayas_rouse/",
      "author": "/u/Adashi_McGay",
      "engagement": 0,
      "metadata": {
        "via": "rss"
      }
    },
    {
      "source": "reddit",
      "time": "2026-06-30T05:18:23+00:00",
      "lang": "en",
      "title": "What I'm running for my speedrun",
      "summary": "&#x200B; #justoutstat (currently a1c9)  &#32; submitted by &#32;  /u/Angbak94   [link] &#32; [comments]",
      "url": "https://old.reddit.com/r/Morimens/comments/1ujg19a/what_im_running_for_my_speedrun/",
      "author": "/u/Angbak94",
      "engagement": 0,
      "media_url": "https://preview.redd.it/kry8atrwtcah1.jpeg?width=640&amp;crop=smart&amp;auto=webp&amp;s=a8ae5db9a1b902756df4beb0517bd8f0b538878b",
      "content_type": "image",
      "metadata": {
        "via": "rss"
      }
    },
    {
      "source": "reddit",
      "time": "2026-06-30T09:44:49+00:00",
      "lang": "en",
      "title": "Team reco",
      "summary": "What&#39;s a good team for caecus and himeln? Cause currently, I pair them with goliath and ramona, but idk if there&#39;s a better awakener that goes well with them  &#32; submitted by &#32;  /u/Conscious-Recipe9498   [link] &#32; [comments]",
      "url": "https://old.reddit.com/r/Morimens/comments/1ujkn7v/team_reco/",
      "author": "/u/Conscious-Recipe9498",
      "engagement": 0,
      "metadata": {
        "via": "rss"
      }
    },
    {
      "source": "reddit",
      "time": "2026-06-30T15:19:10+00:00",
      "lang": "en",
      "title": "I want to make more teams!",
      "summary": "Hi ya! Been really into this game of recent and I was just wondering what other teams I could make? I main nymph because I love her so my main team is nymph xu thais and faint.  If you could then add what rotations I should do that would be great!   &#32; submitted by &#32;  /u/hadalife-   [link] &#32; [comments]",
      "url": "https://old.reddit.com/r/Morimens/comments/1ujs5ex/i_want_to_make_more_teams/",
      "author": "/u/hadalife-",
      "engagement": 0,
      "media_url": "https://preview.redd.it/ogwzp653tfah1.jpg?width=140&amp;height=64&amp;auto=webp&amp;s=97e9ed207985cd26bebfc6422d6c0bacf42c5c1b",
      "content_type": "image",
      "metadata": {
        "via": "rss"
      }
    },
    {
      "source": "reddit",
      "time": "2026-06-30T01:30:50+00:00",
      "lang": "en",
      "title": "With wonderland diary, all the e3 or below awakeners can overexalt?",
      "summary": "Isn&#39;t that broken? Like I can wait for 3 turns and then go over exalt on my e3 gmurphy? I still only have e1, but will try this  &#32; submitted by &#32;  /u/Then-Scale-9476   [link] &#32; [comments]",
      "url": "https://old.reddit.com/r/Morimens/comments/1ujbbob/with_wonderland_diary_all_the_e3_or_below/",
      "author": "/u/Then-Scale-9476",
      "engagement": 0,
      "metadata": {
        "via": "rss"
      }
    },
    {
      "source": "reddit",
      "time": "2026-06-30T04:58:07+00:00",
      "lang": "en",
      "title": "Which teams are good for my characters?",
      "summary": "I&#39;ve been playing since early 2025 and have just been building teams that contain my favorite characters. I&#39;ve got zero idea on the meta and I haven&#39;t touched p-dive &amp; d-zone. I play traphase by just copying teams that I lost against. Please help me.  &#32; submitted by &#32;  /u/CryptographerNo87   [link] &#32; [comments]",
      "url": "https://old.reddit.com/r/Morimens/comments/1ujfn16/which_teams_are_good_for_my_characters/",
      "author": "/u/CryptographerNo87",
      "engagement": 0,
      "media_url": "https://preview.redd.it/f49ad1jzocah1.png?width=140&amp;height=97&amp;auto=webp&amp;s=8dedad1bff2a6c613ae92ebd839434737b9925ab",
      "content_type": "image",
      "metadata": {
        "via": "rss"
      }
    }
  ]
}