{
  "date": "2026-05-14",
  "archived_at": "2026-05-14T06:18:18.185682+00:00",
  "source": "youtube",
  "item_count": 1,
  "items": [
    {
      "source": "youtube",
      "time": "2026-05-13T09:30:34.134432+00:00",
      "lang": "",
      "title": "[Morimens] Updated 2026 \"10 Commandments\" of Morimens for New Players. Everything you should know",
      "summary": "[10 hours ago] https://buymeacoffee.com/flares https://discord.gg/tpMMe5W7CT - Personal Flares Discord ...",
      "url": "https://www.youtube.com/watch?v=yP37qYocHNY",
      "author": "Flares117",
      "engagement": 707,
      "media_url": "https://i.ytimg.com/vi/yP37qYocHNY/hq720.jpg?sqp=-oaymwEcCNAFEJQDSFXyq4qpAw4IARUAAIhCGAFwAcABBg==&rs=AOn4CLAjjN5wacwS2Vq1ynSnmhAgOKPmpw",
      "content_type": "image"
    }
  ]
}