{
  "date": "2026-05-18",
  "archived_at": "2026-05-18T14:29:36.660652+00:00",
  "source": "youtube",
  "item_count": 26,
  "items": [
    {
      "source": "youtube",
      "time": "2026-05-17T23:47:42.421387+00:00",
      "lang": "",
      "title": "【忘卻前夜】小心！這遊戲有降SAN值的精神傷害？😱超硬派克蘇魯策略卡牌遊戲！▹璐洛洛◃",
      "summary": "[2y ago] 遊戲內營造的詭異殘酷的氛圍真的會讓人毛骨悚然呢！   喜歡克蘇魯題材的肉肉不要錯過這款遊戲洛！ 禁忌卡牌構築手遊《忘卻 ...",
      "url": "https://www.youtube.com/watch?v=BomtFzUb12M",
      "author": "璐洛洛 Ruroro【人造人Vtuber】",
      "engagement": 38573,
      "media_url": "https://i.ytimg.com/vi/BomtFzUb12M/hq720.jpg?sqp=-oaymwEcCNAFEJQDSFXyq4qpAw4IARUAAIhCGAFwAcABBg==&rs=AOn4CLA__vo9XU1i-8SMkKg9IqqRgPAvLQ",
      "content_type": "image"
    },
    {
      "source": "youtube",
      "time": "2026-05-17T23:47:42.421438+00:00",
      "lang": "",
      "title": "【忘卻前夜】重返未來1999？不對！是忘卻前夜！禮包碼兌換！T0角色隊伍組合！超少見克蘇魯策略卡牌遊戲！",
      "summary": "[2y ago] 大家好我是歐昊喜歡我的影片可以幫我按喜歡與訂閱我唷有問題也歡迎大家留言感謝大家LDSpace模擬器 ...",
      "url": "https://www.youtube.com/watch?v=37fhxtEUMIM",
      "author": "歐昊",
      "engagement": 16317,
      "media_url": "https://i.ytimg.com/vi/37fhxtEUMIM/hq720.jpg?sqp=-oaymwEcCNAFEJQDSFXyq4qpAw4IARUAAIhCGAFwAcABBg==&rs=AOn4CLCHxBJh287BpFoNLIzuq2ThapmWaw",
      "content_type": "image"
    },
    {
      "source": "youtube",
      "time": "2026-05-17T23:47:42.421476+00:00",
      "lang": "",
      "title": "[The Eve of Oblivion] Oh, this one won't sell! [Smartphone Game Review]",
      "summary": "[7mo ago] This is a review of \"Eve of Oblivion,\" a combination of a Spire-style deck-building roguelike and a chapter-based smartphone ...",
      "url": "https://www.youtube.com/watch?v=7yoi1NyxUHo",
      "author": "あそぶの最新スマホゲームレビュー(中辛)",
      "engagement": 9606,
      "media_url": "https://i.ytimg.com/vi/7yoi1NyxUHo/hq720.jpg?sqp=-oaymwEcCNAFEJQDSFXyq4qpAw4IARUAAIhCGAFwAcABBg==&rs=AOn4CLDha4Az8vbq8k5-Ptf8Y8NbUCwOjw",
      "content_type": "image"
    },
    {
      "source": "youtube",
      "time": "2026-05-17T23:47:42.421490+00:00",
      "lang": "",
      "title": "忘却前夜",
      "summary": "[9mo ago] 忘却前夜の事前登録が正式スタート！ ──・・──・・──・・──・・──・ 世界は静かに確実に終焉へと向かっている この ...",
      "url": "https://www.youtube.com/watch?v=TYFswcPYapE",
      "author": "忘却前夜【日本版公式】",
      "engagement": 4670,
      "media_url": "https://i.ytimg.com/vi/TYFswcPYapE/hq720.jpg?sqp=-oaymwE2CNAFEJQDSFXyq4qpAygIARUAAIhCGAFwAcABBvABAfgB_gmAAtAFigIMCAAQARhlIGUoZTAP&rs=AOn4CLAxfDSfoPSih1ASthkIkcKhaJW07w",
      "content_type": "image"
    },
    {
      "source": "youtube",
      "time": "2026-05-17T23:47:42.421407+00:00",
      "lang": "",
      "title": "【忘卻前夜】半週年入坑指南 組隊的基本概念",
      "summary": "[1y ago] 忘卻前夜#忘卻前夜攻略這是半週年入坑指南的第二期恆燐發現有很多小萌新對組隊有一些小問題所以就出一部短短的影片來說明下一 ...",
      "url": "https://www.youtube.com/watch?v=d89k4tsh7dM",
      "author": "恆燐",
      "engagement": 3623,
      "media_url": "https://i.ytimg.com/vi/d89k4tsh7dM/hqdefault.jpg?sqp=-oaymwEcCOADEI4CSFXyq4qpAw4IARUAAIhCGAFwAcABBg==&rs=AOn4CLBIjMH56dowen-bzxxIsnAlXBFJWA",
      "content_type": "image"
    },
    {
      "source": "youtube",
      "time": "2026-05-17T23:47:42.421463+00:00",
      "lang": "",
      "title": "忘却前夜丨V2.4 PV——「永世虚妄巡礼」（CV：能登麻美子）",
      "summary": "[5mo ago] 睡呀睡，海的小宝贝。” “你的摇篮是黑色的月亮，把群星吞进梦乡……” ✦ 诞妄·墨菲CV：能登麻美子#Morimens #忘卻前夜#誕妄墨 ...",
      "url": "https://www.youtube.com/watch?v=FE1S6a6GPwc",
      "author": "Morimens",
      "engagement": 3570,
      "media_url": "https://i.ytimg.com/vi/FE1S6a6GPwc/hq720.jpg?sqp=-oaymwEcCNAFEJQDSFXyq4qpAw4IARUAAIhCGAFwAcABBg==&rs=AOn4CLCGGpRf098cozzvXhR2xfalMFzL7g",
      "content_type": "image"
    },
    {
      "source": "youtube",
      "time": "2026-05-17T23:47:42.421423+00:00",
      "lang": "",
      "title": "【忘卻前夜】隊伍太多了！多給恆燐幾分鐘 我們來好好聊聊羊媽的隊伍推薦",
      "summary": "[1y ago] 忘卻前夜#忘卻前夜攻略繼續來講羊媽的組隊部分這次把隊伍的部分補齊！ 如果有什麼想法都可以在留言區告訴恆燐！ 另外感謝科目 ...",
      "url": "https://www.youtube.com/watch?v=5bo7iFeZSfE",
      "author": "恆燐",
      "engagement": 2327,
      "media_url": "https://i.ytimg.com/vi/5bo7iFeZSfE/hqdefault.jpg?sqp=-oaymwEcCOADEI4CSFXyq4qpAw4IARUAAIhCGAFwAcABBg==&rs=AOn4CLACqjIIndKN1b3IEf0RZ2_DwAewPw",
      "content_type": "image"
    },
    {
      "source": "youtube",
      "time": "2026-05-17T23:47:42.421431+00:00",
      "lang": "",
      "title": "【忘卻前夜】彌一刀 Arc2.3-10葬骸之主 Miryam one punch #morimens",
      "summary": "[9mo ago] 打完才發現這是普通難度，我破防了。 After I finished playing, I realized that this was normal difficulty, I was crushed. 彌利亞姆星天 ...",
      "url": "https://www.youtube.com/watch?v=KPaSV30cO54",
      "author": "Ernest艾恩斯特",
      "engagement": 1190,
      "media_url": "https://i.ytimg.com/vi/KPaSV30cO54/hq720.jpg?sqp=-oaymwEcCNAFEJQDSFXyq4qpAw4IARUAAIhCGAFwAcABBg==&rs=AOn4CLDM2PJokpesTJh_oaZjUhyPFUXUtA",
      "content_type": "image"
    },
    {
      "source": "youtube",
      "time": "2026-05-18T06:44:07.656241+00:00",
      "lang": "",
      "title": "【忘卻前夜】杜勒賽因的詳細解析！讓坐在餐桌上的恆燐跟你聊聊！技能解說/啟靈/命輪推薦/密契推薦/組隊攻略！",
      "summary": "[9mo ago] 忘卻前夜#克蘇魯神話#莫爾迪基安生命靠自相殘食生存正在殘食生命的我某時也會被生命殘食要是我吃起來很美味那真是再好不過了 ...",
      "url": "https://www.youtube.com/watch?v=K4ibslN8Mus",
      "author": "恆燐",
      "engagement": 1121,
      "media_url": "https://i.ytimg.com/vi/K4ibslN8Mus/hqdefault.jpg?sqp=-oaymwEcCOADEI4CSFXyq4qpAw4IARUAAIhCGAFwAcABBg==&rs=AOn4CLDqawrdN-jEbZsYLBgtu1t_WYKVZg",
      "content_type": "image"
    },
    {
      "source": "youtube",
      "time": "2026-05-18T06:44:07.656304+00:00",
      "lang": "",
      "title": "【忘卻前夜】克萊門汀的詳細解析！依照她的指引！來一場走向痊癒的旅程！喚醒體原型/技能解說/啟靈/命輪推薦/密契推薦/組隊攻略/抽取建議！",
      "summary": "[1y ago] 忘卻前夜#克蘇魯神話#夏蓋蟲族我們心靈的深處到底埋藏著什麼樣的秘密呢？ 放輕鬆！來到克萊門汀的診間來一場窺視靈魂的旅程！",
      "url": "https://www.youtube.com/watch?v=k3np7E92DUI",
      "author": "恆燐",
      "engagement": 961,
      "media_url": "https://i.ytimg.com/vi/k3np7E92DUI/hqdefault.jpg?sqp=-oaymwEcCOADEI4CSFXyq4qpAw4IARUAAIhCGAFwAcABBg==&rs=AOn4CLAalwmQyYRjQ37DA9fRrtocRjl6wg",
      "content_type": "image"
    },
    {
      "source": "youtube",
      "time": "2026-05-18T06:44:07.656318+00:00",
      "lang": "",
      "title": "忘卻前夜 Morimens Everbright Nightfall - Age of Innocence Madness",
      "summary": "[6mo ago] Been a while, college is a lot so even now this might not be regular but I did want to at least do something for Pollux since I really ...",
      "url": "https://www.youtube.com/watch?v=_JKYsyEeSrI",
      "author": "Kiro Takahashi",
      "engagement": 738,
      "media_url": "https://i.ytimg.com/vi/_JKYsyEeSrI/hq720.jpg?sqp=-oaymwEcCNAFEJQDSFXyq4qpAw4IARUAAIhCGAFwAcABBg==&rs=AOn4CLDTnUwsAk7qyeyf7cUJOSwgKq0TVg",
      "content_type": "image"
    },
    {
      "source": "youtube",
      "time": "2026-05-17T23:47:42.421373+00:00",
      "lang": "",
      "title": "【血の鎖ヘロット】やべぇ奴が来た。性能チェックの時間だぁ！！【忘却前夜/ローグライクで遊ぼうの会】",
      "summary": "[Streamed 2w ago] 忘却前夜 #忘却前夜Steam版 見た目もそうだけど、これはやばそうな予感すごいわよ 扱いきれるんですか！？ 提供：株式会社 ...",
      "url": "https://www.youtube.com/watch?v=PVqVgcpSr4A",
      "author": "朝霧@ASGRgames",
      "engagement": 474,
      "media_url": "https://i.ytimg.com/vi/PVqVgcpSr4A/hqdefault.jpg?sqp=-oaymwEcCOADEI4CSFXyq4qpAw4IARUAAIhCGAFwAcABBg==&rs=AOn4CLDYifPbkbt3Mv4gTcRGzZatTXnlrQ",
      "content_type": "image"
    },
    {
      "source": "youtube",
      "time": "2026-05-17T23:47:42.421416+00:00",
      "lang": "",
      "title": "【忘卻前夜】神國毒隊 Arc2.H4-10永恆面紗 三星 Lemuria poison team #morimens",
      "summary": "[5mo ago] 誕妄•墨菲黑暗隱密榨取彌利亞姆虔誠隕日荒原法洛思暴雨腐朽荒原熔燬•朵爾虛無演算荒原#忘卻前夜#morimens.",
      "url": "https://www.youtube.com/watch?v=73Rqnv8zpLs",
      "author": "Ernest艾恩斯特",
      "engagement": 458,
      "media_url": "https://i.ytimg.com/vi/73Rqnv8zpLs/hq720.jpg?sqp=-oaymwEcCNAFEJQDSFXyq4qpAw4IARUAAIhCGAFwAcABBg==&rs=AOn4CLB3bDZe-YRxxphFFKDa-zFVliI-NQ",
      "content_type": "image"
    },
    {
      "source": "youtube",
      "time": "2026-05-17T23:47:42.421455+00:00",
      "lang": "",
      "title": "【忘却前夜】タイスリッツでボス覚醒体を1ターン",
      "summary": "[4mo ago] リッツ、あんま目立ってないけど個性が唯一無二で面白い.",
      "url": "https://www.youtube.com/watch?v=7vS7ZwBBQ5c",
      "author": "愛鳴",
      "engagement": 417,
      "media_url": "https://i.ytimg.com/vi/7vS7ZwBBQ5c/hq720.jpg?sqp=-oaymwE2CNAFEJQDSFXyq4qpAygIARUAAIhCGAFwAcABBvABAfgBvgeAAtAFigIMCAAQARhPIEYoZTAP&rs=AOn4CLCATagQgF4KHFneDsSSGVcDucv9rg",
      "content_type": "image"
    },
    {
      "source": "youtube",
      "time": "2026-05-18T06:44:07.656298+00:00",
      "lang": "",
      "title": "【忘卻前夜】超海水船 Arc2.H3-10葬骸之主 三星 Ultra-Aequor Corpo-Aurita #morimens",
      "summary": "[6mo ago] 卡茜亞的靈塑對餘波隊有提升嗎？感覺是有的。 餘波隊需要這個提升嗎？感覺是不需要的。 Dose Casia' shape benefits the ...",
      "url": "https://www.youtube.com/watch?v=9NgWYuP9HEY",
      "author": "Ernest艾恩斯特",
      "engagement": 409,
      "media_url": "https://i.ytimg.com/vi/9NgWYuP9HEY/hq720.jpg?sqp=-oaymwEcCNAFEJQDSFXyq4qpAw4IARUAAIhCGAFwAcABBg==&rs=AOn4CLBjIdxC_fA9RXyd6pEHZpXxQxHQsA",
      "content_type": "image"
    },
    {
      "source": "youtube",
      "time": "2026-05-17T10:44:16.241986+00:00",
      "lang": "",
      "title": "[Morimens] +12 Ultra AA Buff Overview (Warning, Wanda Slander)",
      "summary": "[6 hours ago] https://buymeacoffee.com/flares https://discord.gg/tpMMe5W7CT - Personal Flares Discord ...",
      "url": "https://www.youtube.com/watch?v=idOJZXpUu7c",
      "author": "Flares117",
      "engagement": 382,
      "media_url": "https://i.ytimg.com/vi/idOJZXpUu7c/hq720.jpg?sqp=-oaymwEcCNAFEJQDSFXyq4qpAw4IARUAAIhCGAFwAcABBg==&rs=AOn4CLA2kBpYK33v4_ROY8dlpzArmH-01Q",
      "content_type": "image"
    },
    {
      "source": "youtube",
      "time": "2026-05-17T23:47:42.421396+00:00",
      "lang": "",
      "title": "【忘卻前夜】血海男團 第47期融災禁區 5-5 Caro-Aequor Boy Band #Morimens",
      "summary": "[6mo ago] 戈利亞安息巨刃紅悸薩爾瓦多神言靈魂二律皮克曼極夜悖謬埋骨泰旖絲慈悲痛楚榨取#忘卻前夜#morimens.",
      "url": "https://www.youtube.com/watch?v=3nALcvwdVz4",
      "author": "Ernest艾恩斯特",
      "engagement": 342,
      "media_url": "https://i.ytimg.com/vi/3nALcvwdVz4/hq720.jpg?sqp=-oaymwEcCNAFEJQDSFXyq4qpAw4IARUAAIhCGAFwAcABBg==&rs=AOn4CLCHONExDm6woduCtci-1gCXasDHxQ",
      "content_type": "image"
    },
    {
      "source": "youtube",
      "time": "2026-05-17T23:47:42.421336+00:00",
      "lang": "",
      "title": "【忘卻前夜/粉絲點名】神國墨主C Arc1.H9-11蚍蜉 三星 Lemuria GMorphy dps #morimens",
      "summary": "[5mo ago] 誕妄•墨菲黑暗隱密榨取彌利亞姆虔誠演算有機戈利亞巨人暴食紅悸凱刻斯靈魂跨越無垢#忘卻前夜#morimens #fanpick.",
      "url": "https://www.youtube.com/watch?v=RAzQFyeIzyQ",
      "author": "Ernest艾恩斯特",
      "engagement": 317,
      "media_url": "https://i.ytimg.com/vi/RAzQFyeIzyQ/hq720.jpg?sqp=-oaymwEcCNAFEJQDSFXyq4qpAw4IARUAAIhCGAFwAcABBg==&rs=AOn4CLDvYdbT16vK-8fJIysyBZiCqpnMZw",
      "content_type": "image"
    },
    {
      "source": "youtube",
      "time": "2026-05-17T17:52:58.604647+00:00",
      "lang": "",
      "title": "[Morimens] Half Anni Pull Guide and Spreadsheet on what to pull, how they work, breakpoints.",
      "summary": "[1 hour ago] https://buymeacoffee.com/flares https://discord.gg/tpMMe5W7CT - Personal Flares Discord ...",
      "url": "https://www.youtube.com/watch?v=_hnlMXglPkE",
      "author": "Flares117",
      "engagement": 209,
      "media_url": "https://i.ytimg.com/vi/_hnlMXglPkE/hq720.jpg?sqp=-oaymwEcCNAFEJQDSFXyq4qpAw4IARUAAIhCGAFwAcABBg==&rs=AOn4CLC6TOHcLZAKylryDuOsICa34xjq4Q",
      "content_type": "image"
    },
    {
      "source": "youtube",
      "time": "2026-05-17T23:47:42.421447+00:00",
      "lang": "",
      "title": "忘卻前夜 幻夢深潛_43200 「沉淵者」_「移湧」 地瓜醫生 混沌超維 #忘卻前夜 #morimens",
      "summary": "[8mo ago] 幻夢深潛#混沌超維#忘卻前夜#morimens.",
      "url": "https://www.youtube.com/watch?v=ArGNulXbHuo",
      "author": "瑪爾",
      "engagement": 193,
      "media_url": "https://i.ytimg.com/vi/ArGNulXbHuo/hq720.jpg?sqp=-oaymwEcCNAFEJQDSFXyq4qpAw4IARUAAIhCGAFwAcABBg==&rs=AOn4CLDGTvyJvVNGRgdY0e6b2EHHrvlkQA",
      "content_type": "image"
    },
    {
      "source": "youtube",
      "time": "2026-05-17T23:47:42.421483+00:00",
      "lang": "",
      "title": "【忘卻前夜/粉絲點名】羊媽主C Arc1.H7-12火種 三星三成就 Goat dps #morimens",
      "summary": "[5mo ago] 泰旖絲黑暗安息36 皮克曼悖謬演算再衍24 摯友虔誠黑子萊克騎士琥珀無垢#忘卻前夜#morimens #fanpick.",
      "url": "https://www.youtube.com/watch?v=878CNWoBqXE",
      "author": "Ernest艾恩斯特",
      "engagement": 164,
      "media_url": "https://i.ytimg.com/vi/878CNWoBqXE/hq720.jpg?sqp=-oaymwEcCNAFEJQDSFXyq4qpAw4IARUAAIhCGAFwAcABBg==&rs=AOn4CLDLA1lUrLnMLA1lSGXibqNsWmV9EQ",
      "content_type": "image"
    },
    {
      "source": "youtube",
      "time": "2026-05-18T09:56:40.614965+00:00",
      "lang": "",
      "title": "[Morimens] Short Livestream PSA Highlight : Gnostic Potential is a huge SCAM for F2P and new players",
      "summary": "[1 hour ago] https://buymeacoffee.com/flares https://discord.gg/tpMMe5W7CT - Personal Flares Discord ...",
      "url": "https://www.youtube.com/watch?v=u_GrgsIXXn0",
      "author": "Flares117",
      "engagement": 115,
      "media_url": "https://i.ytimg.com/vi/u_GrgsIXXn0/hq720.jpg?sqp=-oaymwEcCNAFEJQDSFXyq4qpAw4IARUAAIhCGAFwAcABBg==&rs=AOn4CLBikG-A11jROUSBY-ayyWMZSAbrOQ",
      "content_type": "image"
    },
    {
      "source": "youtube",
      "time": "2026-05-17T20:24:35.038832+00:00",
      "lang": "",
      "title": "[Morimens] 2026 Wheel Guide for Morimens. Is Wheel Jail still a thing? (yes)",
      "summary": "[28 minutes ago] https://buymeacoffee.com/flares https://discord.gg/tpMMe5W7CT - Personal Flares Discord ...",
      "url": "https://www.youtube.com/watch?v=pr1zkBZ5UJg",
      "author": "Flares117",
      "engagement": 80,
      "media_url": "https://i.ytimg.com/vi/pr1zkBZ5UJg/hq720.jpg?sqp=-oaymwEcCNAFEJQDSFXyq4qpAw4IARUAAIhCGAFwAcABBg==&rs=AOn4CLDiYwqzSi_0zezPg-Y6JcCi4vNyIg",
      "content_type": "image"
    },
    {
      "source": "youtube",
      "time": "2026-05-17T23:47:42.421470+00:00",
      "lang": "",
      "title": "【忘却前夜】ゴリアテを使いたい！",
      "summary": "[3w ago] 忘却前夜 #忘却前夜Steam版 提供：株式会社オルトプラス.",
      "url": "https://www.youtube.com/watch?v=XGhnYfiYZ1g",
      "author": "じゃく",
      "engagement": 65,
      "media_url": "https://i.ytimg.com/vi/XGhnYfiYZ1g/hq720.jpg?sqp=-oaymwEcCNAFEJQDSFXyq4qpAw4IARUAAIhCGAFwAcABBg==&rs=AOn4CLAuRWW-ROcFgUiFSXES0HCKpDSnCw",
      "content_type": "image"
    },
    {
      "source": "youtube",
      "time": "2026-05-17T18:52:58.604887+00:00",
      "lang": "",
      "title": "[Morimens] LOOOONG? Boring Spreadsheet stream/light coaching overview.",
      "summary": "Long Boring Spreadsheet stream. And making next video.",
      "url": "https://www.youtube.com/watch?v=V3E7Fav8rwg",
      "author": "Flares117",
      "engagement": 0,
      "media_url": "https://i.ytimg.com/vi/V3E7Fav8rwg/hq720.jpg?v=6a09d0ca&sqp=-oaymwEcCNAFEJQDSFXyq4qpAw4IARUAAIhCGAFwAcABBg==&rs=AOn4CLBnlRI33JNqbYV8LXNjCab7k4fbTg",
      "content_type": "image"
    },
    {
      "source": "youtube",
      "time": "2026-05-18T10:56:40.615153+00:00",
      "lang": "",
      "title": "[Morimens] Short (Relatively) Anni testing stream for some content",
      "summary": "Long Boring Spreadsheet stream. And making next video.",
      "url": "https://www.youtube.com/watch?v=0bds-wZTsko",
      "author": "Flares117",
      "engagement": 0,
      "media_url": "https://i.ytimg.com/vi/0bds-wZTsko/hq720.jpg?v=6a0ace4a&sqp=-oaymwEcCNAFEJQDSFXyq4qpAw4IARUAAIhCGAFwAcABBg==&rs=AOn4CLCCcdRubkTdd9PxpWA0FmKIWQaLRw",
      "content_type": "image"
    }
  ]
}